Topsis/__init__.py
Topsis/topsis.py
topsis_ayush_kaushik_102303104-0.1.dist-info/LICENSE.txt
topsis_ayush_kaushik_102303104-0.1.dist-info/METADATA
topsis_ayush_kaushik_102303104-0.1.dist-info/WHEEL
topsis_ayush_kaushik_102303104-0.1.dist-info/top_level.txt
topsis_ayush_kaushik_102303104-0.1.dist-info/RECORD
