Metadata-Version: 2.1
Name: topsis-ayush-kaushik-102303104
Version: 0.1
Summary: A Topsis Report Generator
Author: Ayush Kaushik
Author-email: akaushik1_be23@thapar.edu
Classifier: Programming Language :: Python :: 3
Classifier: License :: OSI Approved :: MIT License
Classifier: Operating System :: OS Independent
License-File: LICENSE.txt
